{"cameraMode":{"drawMode":0,"name":"Shaded","section":"Shading Mode"},"sceneLighting":false,"audioPlay":false,"sceneViewState":{"showFog":true,"showMaterialUpdate":false,"showSkybox":false,"showFlares":true,"showImageEffects":true,"showParticleSystems":true},"in2DMode":false,"pivot":{"x":11.519865036010743,"y":0.07800006866455078,"z":-2.1900553703308107},"rotation":{"x":-0.09929659962654114,"y":0.8818696141242981,"z":-0.21469588577747346,"w":-0.407863587141037},"size":7.9593939781188969,"orthographic":false}